content_studio/__init__.py
content_studio/admin.py
content_studio/apps.py
content_studio/dashboard/__init__.py
content_studio/dashboard/activity_log.py
content_studio/dashboard/statistic.py
content_studio/filters.py
content_studio/form.py
content_studio/formats.py
content_studio/login_backends/__init__.py
content_studio/login_backends/username_password.py
content_studio/media_library/serializers.py
content_studio/media_library/viewsets.py
content_studio/models.py
content_studio/paginators.py
content_studio/router.py
content_studio/serializers.py
content_studio/settings.py
content_studio/static/content_studio/assets/browser-ponyfill-TyWUZ1Oq.js
content_studio/static/content_studio/assets/index.css
content_studio/static/content_studio/assets/index.js
content_studio/static/content_studio/icons/pi/Phosphor-Bold.svg
content_studio/static/content_studio/icons/pi/Phosphor-Bold.ttf
content_studio/static/content_studio/icons/pi/Phosphor-Bold.woff
content_studio/static/content_studio/icons/pi/Phosphor-Bold.woff2
content_studio/static/content_studio/icons/pi/style.css
content_studio/static/content_studio/img/media_placeholder.svg
content_studio/static/content_studio/index.html
content_studio/static/content_studio/locales/en/translation.json
content_studio/static/content_studio/locales/nl/translation.json
content_studio/static/content_studio/vite.svg
content_studio/templates/content_studio/index.html
content_studio/token_backends/__init__.py
content_studio/token_backends/jwt.py
content_studio/urls.py
content_studio/utils.py
content_studio/views.py
content_studio/viewsets.py
content_studio/widgets.py
django_content_studio-1.0.0b10.post1.dist-info/LICENSE
django_content_studio-1.0.0b10.post1.dist-info/METADATA
django_content_studio-1.0.0b10.post1.dist-info/WHEEL
django_content_studio-1.0.0b10.post1.dist-info/RECORD
