Metadata-Version: 2.3
Name: django-content-studio
Version: 1.0.0b10.post1
Summary: Modern & flexible Django admin
License: MIT
Author: Leon van der Grient
Author-email: leon@devtastic.io
Requires-Python: >=3.10
Classifier: License :: OSI Approved :: MIT License
Classifier: Programming Language :: Python :: 3
Classifier: Programming Language :: Python :: 3.10
Classifier: Programming Language :: Python :: 3.11
Classifier: Programming Language :: Python :: 3.12
Classifier: Programming Language :: Python :: 3.13
